webdav2/__init__.py
webdav2/client.py
webdav2/connection.py
webdav2/exceptions.py
webdav2/urn.py
webdavclient2-0.1.1.data/scripts/wdc
webdavclient2-0.1.1.dist-info/DESCRIPTION.rst
webdavclient2-0.1.1.dist-info/METADATA
webdavclient2-0.1.1.dist-info/RECORD
webdavclient2-0.1.1.dist-info/WHEEL
webdavclient2-0.1.1.dist-info/metadata.json
webdavclient2-0.1.1.dist-info/top_level.txt
