Metadata-Version: 2.0
Name: webdavclient2
Version: 0.1.1
Summary: WebDAV client, based on original package https://github.com/designerror/webdav-client-python but uses requests instead of PyCURL
Home-page: https://github.com/appetito/webdav-client-python-2
Author: Yuriy Homyakov
Author-email: yuriy.homyakov@gmail.com
License: MIT License
Keywords: webdav,client,python,module,library,packet,Yandex.Disk,Dropbox,Google Disk,Box,4shared
Platform: UNKNOWN
Classifier: Environment :: Console
Classifier: Environment :: Web Environment
Classifier: License :: OSI Approved :: MIT License
Classifier: Operating System :: MacOS
Classifier: Operating System :: Microsoft
Classifier: Operating System :: Unix
Classifier: Programming Language :: Python :: 2.6
Classifier: Programming Language :: Python :: 2.7
Classifier: Programming Language :: Python :: 3.0
Classifier: Programming Language :: Python :: 3.1
Classifier: Programming Language :: Python :: 3.2
Classifier: Programming Language :: Python :: 3.3
Classifier: Programming Language :: Python :: 3.4
Classifier: Topic :: Internet
Classifier: Topic :: Software Development :: Libraries :: Python Modules
Requires: python (>= 2.7.6)
Requires-Dist: lxml
Requires-Dist: requests
